mpi_ioc/__init__.py
mpi_ioc/mpi_ioc.py
mpi_ioc-0.1.2.dist-info/DESCRIPTION.rst
mpi_ioc-0.1.2.dist-info/METADATA
mpi_ioc-0.1.2.dist-info/RECORD
mpi_ioc-0.1.2.dist-info/WHEEL
mpi_ioc-0.1.2.dist-info/metadata.json
mpi_ioc-0.1.2.dist-info/top_level.txt
