Metadata-Version: 2.0
Name: mpi-ioc
Version: 0.1.2
Summary: Framework for demonstrating the use of such a framework for MPI applications.
Home-page: https://github.com/rchuso/mpi_ioc
Author: Rand Cary Huso
Author-email: rchuso@gmail.com
License: ISCL
Keywords: IoC,MPI,framework,development
Platform: UNKNOWN
Classifier: Development Status :: 2 - Pre-Alpha
Classifier: Intended Audience :: Developers
Classifier: License :: OSI Approved :: ISC License (ISCL)
Classifier: Natural Language :: English
Classifier: Programming Language :: Python :: 3
Classifier: Programming Language :: Python :: 3.2
Classifier: Programming Language :: Python :: 3.3
Classifier: Programming Language :: Python :: 3.4
Classifier: Programming Language :: Python :: 3.5
Requires-Dist: mpi4py
Requires-Dist: psutil
